pydemia
