Metadata-Version: 1.1
Name: pydemia
Version: 0.1.10
Summary: Useful tools for Analysis
Home-page: http://github.com/pydemia/pydemia
Author: Young Ju Kim
Author-email: pydemia@gmail.com
License: MIT License
Platform: UNKNOWN
Classifier: Development Status :: 3 - Alpha
Classifier: Programming Language :: Python :: 3.5
